htmldoom/__init__.py
htmldoom/base.py
htmldoom/conf.py
htmldoom/elements.py
htmldoom/functions.py
htmldoom/url.py
htmldoom/util.py
htmldoom/value_loader.py
htmldoom/yaml_loader.py
htmldoom-1.0.1.dist-info/LICENSE
htmldoom-1.0.1.dist-info/METADATA
htmldoom-1.0.1.dist-info/WHEEL
htmldoom-1.0.1.dist-info/top_level.txt
htmldoom-1.0.1.dist-info/RECORD
