Metadata-Version: 2.1
Name: htmldoom
Version: 1.0.1
Summary: An intuitive, high performance HTML rendering framework
Home-page: https://github.com/sayanarijit/htmldoom
Author: Arijit Basu
Author-email: sayanarijit@gmail.com
License: MIT
Keywords: html rendering framework
Platform: Any
Classifier: Development Status :: 5 - Production/Stable
Classifier: Environment :: Web Environment
Classifier: Intended Audience :: Developers
Classifier: Intended Audience :: Information Technology
Classifier: Intended Audience :: Other Audience
Classifier: License :: OSI Approved :: MIT License
Classifier: Programming Language :: Python
Classifier: Programming Language :: Python :: 3.6
Classifier: Programming Language :: Python :: 3.7
Classifier: Topic :: Software Development :: Libraries
Classifier: Topic :: Software Development :: Libraries :: Python Modules
Provides-Extra: testing
Provides-Extra: dev
